setup.py
virtualenv_hax.py
virtualenv_hax.egg-info/PKG-INFO
virtualenv_hax.egg-info/SOURCES.txt
virtualenv_hax.egg-info/dependency_links.txt
virtualenv_hax.egg-info/entry_points.txt
virtualenv_hax.egg-info/pbr.json
virtualenv_hax.egg-info/requires.txt
virtualenv_hax.egg-info/top_level.txt