Metadata-Version: 1.1
Name: virtualenv-hax
Version: 0.0.1
Summary: A wrapper around virtualenv that avoids sys.path sadness.
Home-page: https://github.com/asottile/virtualenv-hax
Author: Anthony Sottile
Author-email: asottile@umich.edu
License: UNKNOWN
Platform: UNKNOWN
Classifier: License :: OSI Approved :: MIT License
Classifier: Programming Language :: Python :: 2
Classifier: Programming Language :: Python :: 2.6
Classifier: Programming Language :: Python :: 2.7
Classifier: Programming Language :: Python :: 3
Classifier: Programming Language :: Python :: 3.3
Classifier: Programming Language :: Python :: 3.4
Classifier: Programming Language :: Python :: Implementation :: CPython
Classifier: Programming Language :: Python :: Implementation :: PyPy
